monitor/__init__.py
monitor/__meta__.py
monitor/cli/__init__.py
monitor/cli/cpu.py
monitor/cli/memory.py
monitor/cli/cpu/__init__.py
monitor/cli/cpu/memory.py
monitor/cli/cpu/percent.py
monitor/cli/gpu/__init__.py
monitor/cli/gpu/memory.py
monitor/cli/gpu/percent.py
monitor/cli/gpu/power.py
monitor/cli/gpu/temp.py
monitor/contrib/__init__.py
monitor/contrib/nvidia.py
monitor/contrib/rocm.py
monitor/core/__init__.py
monitor/core/exceptions.py
monitor/core/extern.py
monitor/core/logging.py
monitor/core/stat.py
resource_monitor-2.3.1.data/data/share/man/man1/monitor.1
resource_monitor-2.3.1.dist-info/LICENSE
resource_monitor-2.3.1.dist-info/METADATA
resource_monitor-2.3.1.dist-info/WHEEL
resource_monitor-2.3.1.dist-info/entry_points.txt
resource_monitor-2.3.1.dist-info/top_level.txt
resource_monitor-2.3.1.dist-info/RECORD
