Metadata-Version: 2.1
Name: resource-monitor
Version: 2.3.1
Summary: A simple cross-platform system resource monitor.
Home-page: https://resource-monitor.readthedocs.io
Author: Geoffrey Lentner
Author-email: glentner@purdue.edu
License: Apache Software License 2.0
Keywords: cross-platform system resource-monitor telemetry utility command-line-tool
Platform: UNKNOWN
Classifier: Development Status :: 5 - Production/Stable
Classifier: Programming Language :: Python :: 3
Classifier: Programming Language :: Python :: 3.7
Classifier: Programming Language :: Python :: 3.8
Classifier: Programming Language :: Python :: 3.9
Classifier: Programming Language :: Python :: 3.10
Classifier: Operating System :: POSIX :: Linux
Classifier: Operating System :: MacOS
Classifier: Operating System :: Microsoft :: Windows
Classifier: Intended Audience :: Information Technology
Classifier: Intended Audience :: System Administrators
Classifier: License :: OSI Approved :: Apache Software License
Classifier: Topic :: System :: Monitoring
License-File: LICENSE
Requires-Dist: cmdkit (==1.5.5)
Requires-Dist: logalpha (==2.0.2)
Requires-Dist: psutil (>=5.7.2)
